receiptcreater/__init__.py
receiptcreater/__main__.py
receiptcreater/proc.py
receiptcreater-0.1.0.dist-info/METADATA
receiptcreater-0.1.0.dist-info/WHEEL
receiptcreater-0.1.0.dist-info/entry_points.txt
receiptcreater-0.1.0.dist-info/top_level.txt
receiptcreater-0.1.0.dist-info/RECORD
