Metadata-Version: 2.1
Name: receiptcreater
Version: 0.1.0
Summary: A package for create receipt
Author-email: Dusya <Lev.khrobostov@mail.ru>
License: MIT
